LICENSE
MANIFEST.in
README.md
setup.py
pysuchsel/ActionCrypto.py
pysuchsel/ActionFontTest.py
pysuchsel/ActionSolutionWord.py
pysuchsel/ActionSuchselCrossword.py
pysuchsel/Alphabet.py
pysuchsel/BaseAction.py
pysuchsel/CryptoPuzzle.py
pysuchsel/Exceptions.py
pysuchsel/FriendlyArgumentParser.py
pysuchsel/MultiCommand.py
pysuchsel/PrefixMatcher.py
pysuchsel/RandomDist.py
pysuchsel/SolutionWordPuzzle.py
pysuchsel/Suchsel.py
pysuchsel/Tools.py
pysuchsel/__init__.py
pysuchsel/__main__.py
pysuchsel/definitions.json
pysuchsel.egg-info/PKG-INFO
pysuchsel.egg-info/SOURCES.txt
pysuchsel.egg-info/dependency_links.txt
pysuchsel.egg-info/entry_points.txt
pysuchsel.egg-info/requires.txt
pysuchsel.egg-info/top_level.txt