Metadata-Version: 2.1
Name: pysuchsel
Version: 0.0.1
Summary: Native Python library to create and edit SVG documents
Home-page: https://github.com/johndoe31415/pysuchsel
Download-URL: https://github.com/johndoe31415/pysuchsel/archive/v0.0.1.tar.gz
Author: Johannes Bauer
Author-email: joe@johannes-bauer.com
License: gpl-3.0
Keywords: puzzle,crossword,suchsel
Classifier: Development Status :: 5 - Production/Stable
Classifier: Intended Audience :: Developers
Classifier: License :: OSI Approved :: GNU General Public License v3 (GPLv3)
Classifier: Programming Language :: Python :: 3
Classifier: Programming Language :: Python :: 3 :: Only
Classifier: Programming Language :: Python :: 3.6
Classifier: Programming Language :: Python :: 3.7
Classifier: Programming Language :: Python :: 3.8
Classifier: Programming Language :: Python :: 3.9
Classifier: Programming Language :: Python :: 3.10
License-File: LICENSE
